orbit_storage/__init__.py
orbit_storage/storage.py
orbit_storage-0.1.dist-info/METADATA
orbit_storage-0.1.dist-info/WHEEL
orbit_storage-0.1.dist-info/entry_points.txt
orbit_storage-0.1.dist-info/top_level.txt
orbit_storage-0.1.dist-info/RECORD
