Metadata-Version: 2.4
Name: orbit_storage
Version: 0.1
Classifier: Programming Language :: Python :: 3
Classifier: License :: OSI Approved :: MIT License
Classifier: Operating System :: OS Independent
Requires-Python: >=3.6
Requires-Dist: requests
Requires-Dist: pyfiglet
Dynamic: classifier
Dynamic: requires-dist
Dynamic: requires-python
